README
setup.py
helper_datetime/__init__.py
helper_datetime.egg-info/PKG-INFO
helper_datetime.egg-info/SOURCES.txt
helper_datetime.egg-info/dependency_links.txt
helper_datetime.egg-info/top_level.txt