Metadata-Version: 1.0
Name: helper-datetime
Version: 0.5
Summary: Date & Time Helper
Home-page: https://github.com/shuge/helper_datetime
Author: Shuge Lee
Author-email: shuge.lee@gmail.com
License: MIT License
Platform: UNKNOWN
